recast/__init__.py
recast/recast.py
recast-0.1.0.dist-info/LICENSE
recast-0.1.0.dist-info/METADATA
recast-0.1.0.dist-info/WHEEL
recast-0.1.0.dist-info/top_level.txt
recast-0.1.0.dist-info/RECORD
