Metadata-Version: 2.1
Name: recast
Version: 0.1.0
Summary: python bit recaster
Home-page: https://github.com/kupad/recast
Author: Phil Dreizen, Miccah Castorina
Author-email: dreizen@kupad.net, m.castorina93@gmail.com
License: UNKNOWN
Project-URL: Bug Tracker, https://github.com/kupad/recast/issues
Platform: UNKNOWN
Classifier: Programming Language :: Python :: 3
Classifier: License :: OSI Approved :: GNU Lesser General Public License v2 (LGPLv2)
Classifier: Operating System :: OS Independent
Requires-Python: >=3.6
License-File: LICENSE
